risk_modeling_tools/__init__.py
risk_modeling_tools/constants.py
risk_modeling_tools/data_processing.py
risk_modeling_tools/optimization.py
risk_modeling_tools/binning/__init__.py
risk_modeling_tools/binning/bin_classes.py
risk_modeling_tools/binning/binning_algorithms.py
risk_modeling_tools/binning/binning_utils.py
risk_modeling_tools/modeling/__init__.py
risk_modeling_tools/modeling/feature_selection.py
risk_modeling_tools/modeling/metrics.py
risk_modeling_tools-0.0.3.dist-info/LICENCE.txt
risk_modeling_tools-0.0.3.dist-info/METADATA
risk_modeling_tools-0.0.3.dist-info/WHEEL
risk_modeling_tools-0.0.3.dist-info/top_level.txt
risk_modeling_tools-0.0.3.dist-info/RECORD
