Metadata-Version: 2.1
Name: risk-modeling-tools
Version: 0.0.3
Summary: Tools for credit risk scoring models development and portfolio management
Home-page: https://github.com/mgrts/risk_modeling_tools
Author: Mikhail Gritskikh
Author-email: m.gritskikh@gmail.com
License: MIT
Keywords: credit,risk,modeling,scoring,binning
Platform: UNKNOWN
Classifier: Development Status :: 5 - Production/Stable
Classifier: Intended Audience :: Financial and Insurance Industry
Classifier: Operating System :: Microsoft :: Windows :: Windows 10
Classifier: License :: OSI Approved :: MIT License
Classifier: Programming Language :: Python :: 3
License-File: LICENCE.txt
Requires-Dist: numpy
Requires-Dist: pandas
Requires-Dist: sklearn
Requires-Dist: scipy
